statsbiblioteket.github_cloner-0.2.0.dist-info/METADATA
statsbiblioteket.github_cloner-0.2.0.dist-info/entry_points.txt
statsbiblioteket.github_cloner-0.2.0.dist-info/RECORD
statsbiblioteket.github_cloner-0.2.0.dist-info/WHEEL
statsbiblioteket.github_cloner-0.2.0.dist-info/top_level.txt
statsbiblioteket.github_cloner-0.2.0.dist-info/DESCRIPTION.rst
statsbiblioteket.github_cloner-0.2.0.dist-info/metadata.json
statsbiblioteket/github_cloner/__main__.py
statsbiblioteket/github_cloner/__init__.py
statsbiblioteket/github_cloner/myTypes.py
statsbiblioteket/github_cloner/github_cloner.py
