Metadata-Version: 2.0
Name: statsbiblioteket.github-cloner
Version: 0.2.0
Summary: Python Command line program for harvesting github repositories
Home-page: https://github.com/blekinge/github_cloner
Author: Asger Askov Blekinge
Author-email: asger.askov.blekinge@gmail.com
License: ISCL
Keywords: github_cloner
Platform: UNKNOWN
Classifier: Development Status :: 4 - Beta
Classifier: Intended Audience :: Developers
Classifier: License :: OSI Approved :: ISC License (ISCL)
Classifier: Natural Language :: English
Classifier: Programming Language :: Python :: 3
Classifier: Programming Language :: Python :: 3.3
Classifier: Programming Language :: Python :: 3.4
Classifier: Programming Language :: Python :: 3.5
Requires-Dist: requests
Requires-Dist: argparse
Requires-Dist: typing
Requires-Dist: enum34
